{"spells" :{
	"blood_sacrifice" :
	{
		"mana" : 0,
		"life" : 1,
		"oplifechange" : 0,
		"plifechange": 0,
		"opmanachange":0,
		"pmanachange":3,
		"description":"Caster loses 1 life to gain 3 mana.",
		"img-url":"public/images/spells/blood_sacrifice.png"

	},
	"fire_ball":
	{
		"mana" : 3,
		"life" : 0,
		"oplifechange" : -3,
		"plifechange":0,
		"opmanachange":0,
		"pmanachange":0,
		"description":"Deals 3 damage to the opponent.",
		"img-url":"public/images/spells/fire_ball.png"
	}
	,
	"heal":
	{
		"mana":1,
		"life":0,
		"oplifechange":0,
		"plifechange":2,
		"opmanachange":0,
		"pmanachange":0,
		"description":"Caster gains 2 life.",
		"img-url":"public/images/spells/heal.png"
	}
	,
	"siphon's_drain":
	{
		"mana":1,
		"life":0,
		"oplifechange":0,
		"plifechange":0,
		"opmanachange":-2,
		"pmanachange":2,
		"description":"Drains 2 mana from opponent.",
		"img-url":"public/images/spells/siphon's_drain.png"
	},
	"disruptive_shift":
	{
		"mana":2,
		"life":0,
		"oplifechange":0,
		"plifechange":0,
		"opmanachange":0,
		"pmanachange":5,
		"description":"Doubles the caster's mana. Cannot exceed opponent's health.",
		"img-url":"public/images/spells/disruptive_shift.png"
	},
	"vampiric_drain":
	{
		"mana":4,
		"life":0,
		"oplifechange":-2,
		"plifechange":2,
		"opmanachange":0,
		"pmanachange":0,
		"description":"Drains 2 life from the opponent.",
		"img-url":"public/images/spells/vampiric_drain.png"
	},
	"chaotic_blast":
	{
		"mana":5,
		"life":0,
		"oplifechange":-5,
		"plifechange":0,
		"opmanachange":0,
		"pmanachange":0,
		"description":"Deals 5 damage to the opponent.",
		"img-url":"public/images/spells/chaotic_blast.png"
	}
}
}
		
